LICENSE
MANIFEST.in
README.md
setup.py
django_tastypiedoc.egg-info/PKG-INFO
django_tastypiedoc.egg-info/SOURCES.txt
django_tastypiedoc.egg-info/dependency_links.txt
django_tastypiedoc.egg-info/top_level.txt
tastypiedoc/__init__.py
tastypiedoc/models.py
tastypiedoc/tests.py
tastypiedoc/urls.py
tastypiedoc/views.py
tastypiedoc/api/__init__.py
tastypiedoc/api/__init__.pyc
tastypiedoc/api/apigenerator.py
tastypiedoc/api/apigenerator.pyc
tastypiedoc/static/.jshintrc
tastypiedoc/static/monitor.sh
tastypiedoc/static/test.txt
tastypiedoc/static/css/style.css
tastypiedoc/static/css/fonts/glyphiconshalflings-regular.eot
tastypiedoc/static/css/fonts/glyphiconshalflings-regular.otf
tastypiedoc/static/css/fonts/glyphiconshalflings-regular.svg
tastypiedoc/static/css/fonts/glyphiconshalflings-regular.ttf
tastypiedoc/static/css/fonts/glyphiconshalflings-regular.woff
tastypiedoc/static/js/doc.js
tastypiedoc/static/js/libs/bootstrap.js
tastypiedoc/static/js/libs/jquery.js
tastypiedoc/static/js/libs/underscore.js
tastypiedoc/static/less/all.less
tastypiedoc/static/less/bootstrap/accordion.less
tastypiedoc/static/less/bootstrap/alerts.less
tastypiedoc/static/less/bootstrap/badges.less
tastypiedoc/static/less/bootstrap/bootstrap.less
tastypiedoc/static/less/bootstrap/breadcrumbs.less
tastypiedoc/static/less/bootstrap/button-groups.less
tastypiedoc/static/less/bootstrap/buttons.less
tastypiedoc/static/less/bootstrap/carousel.less
tastypiedoc/static/less/bootstrap/close.less
tastypiedoc/static/less/bootstrap/code.less
tastypiedoc/static/less/bootstrap/component-animations.less
tastypiedoc/static/less/bootstrap/dropdowns.less
tastypiedoc/static/less/bootstrap/forms.less
tastypiedoc/static/less/bootstrap/glyphicons.less
tastypiedoc/static/less/bootstrap/grid.less
tastypiedoc/static/less/bootstrap/jumbotron.less
tastypiedoc/static/less/bootstrap/labels.less
tastypiedoc/static/less/bootstrap/list-group.less
tastypiedoc/static/less/bootstrap/media.less
tastypiedoc/static/less/bootstrap/mixins.less
tastypiedoc/static/less/bootstrap/modals.less
tastypiedoc/static/less/bootstrap/navbar.less
tastypiedoc/static/less/bootstrap/navs.less
