Metadata-Version: 1.1
Name: django-tastypiedoc
Version: 0.2.2
Summary: A simple Django app to explore tastypie APIs.
Home-page: http://www.hiiamchris.com/
Author: Chris Duranti
Author-email: chrisd1891@gmail.com
License: MIT License
Platform: UNKNOWN
Classifier: Environment :: Web Environment
Classifier: Framework :: Django
Classifier: Intended Audience :: Developers
Classifier: Operating System :: OS Independent
Classifier: Programming Language :: Python
Classifier: Programming Language :: Python :: 2
Classifier: Programming Language :: Python :: 2.7
Classifier: Topic :: Internet :: WWW/HTTP
Classifier: Topic :: Internet :: WWW/HTTP :: Dynamic Content
